mj_helpers-0.0.0.dist-info/METADATA
mj_helpers-0.0.0.dist-info/WHEEL
mj_helpers-0.0.0.dist-info/pbr.json
mj_helpers-0.0.0.dist-info/metadata.json
mj_helpers-0.0.0.dist-info/RECORD
mj_helpers-0.0.0.dist-info/entry_points.txt
mj_helpers-0.0.0.dist-info/top_level.txt
mj_helpers-0.0.0.dist-info/DESCRIPTION.rst
mj_helpers/__init__.py
mj_helpers/profileit.py
mj_helpers/log_decorator.py
mj_helpers/mj_stats.py
