Metadata-Version: 2.0
Name: mj-helpers
Version: 0.0.0
Summary: A collection of helper functions and decorators that I occasionally use to get my life in order.
Home-page: https://github.com/mikejarrett/mj-helpers
Author: Mike Jarrett
Author-email: mike.d.jarrett at gmail dot com
License: MIT
Keywords: logging profiling decorators
Platform: UNKNOWN
Classifier: Development Status :: 3 - Alpha
Classifier: Intended Audience :: Developers
Classifier: Topic :: Software Development
Classifier: License :: OSI Approved :: MIT License
Classifier: Programming Language :: Python :: 2
Classifier: Programming Language :: Python :: 2.6
Classifier: Programming Language :: Python :: 2.7
Classifier: Programming Language :: Python :: 3
Classifier: Programming Language :: Python :: 3.2
Classifier: Programming Language :: Python :: 3.3
Classifier: Programming Language :: Python :: 3.4
Provides-Extra: dev
Requires-Dist: check-manifest; extra == 'dev'
Provides-Extra: test
Requires-Dist: coverage; extra == 'test'
